LICENSE
hypothesis_jsonrpc/__init__.py
hypothesis_jsonrpc/py.typed
hypothesis_jsonrpc/strategies.py
hypothesis_jsonrpc-2.0.0.dist-info/LICENSE
hypothesis_jsonrpc-2.0.0.dist-info/WHEEL
hypothesis_jsonrpc-2.0.0.dist-info/METADATA
hypothesis_jsonrpc-2.0.0.dist-info/RECORD
