Metadata-Version: 2.1
Name: hypothesis-jsonrpc
Version: 2.0.0
Summary: Hypothesis strategy to generate JSON-RPC 2.0
Home-page: https://github.com/macheins/hypothesis-jsonrpc
License: UNKOWN
Author: macheins
Requires-Python: >=3.5,<4.0
Classifier: Development Status :: 5 - Production/Stable
Classifier: Intended Audience :: Developers
Classifier: License :: OSI Approved
Classifier: License :: OSI Approved :: MirOS License (MirOS)
Classifier: Programming Language :: Python :: 3
Classifier: Programming Language :: Python :: 3 :: Only
Classifier: Programming Language :: Python :: 3.5
Classifier: Programming Language :: Python :: 3.6
Classifier: Programming Language :: Python :: 3.7
Classifier: Topic :: Software Development :: Testing
Requires-Dist: hypothesis (>=3.71,<4.0)
Requires-Dist: hypothesis-json (>=1.2,<2.0)
